README.md
setup.cfg
setup.py
pyproba/Binomialdistribution.py
pyproba/Gaussiandistribution.py
pyproba/Generaldistribution.py
pyproba/__init__.py
pyproba.egg-info/PKG-INFO
pyproba.egg-info/SOURCES.txt
pyproba.egg-info/dependency_links.txt
pyproba.egg-info/not-zip-safe
pyproba.egg-info/top_level.txt