Metadata-Version: 1.0
Name: pyproba
Version: 1.0.1
Summary: Exploring Probability distributions
Home-page: https://github.com/adityakalra581/pyproba
Author: Aditya Kalra
Author-email: adityakalra581@gmail.com
License: UNKNOWN
Keywords: probability-distribution
Platform: UNKNOWN
